ddg2rss/__init__.py
ddg2rss/generator.py
ddg2rss/test_generator.py
ddg2rss-1.0.1.dist-info/LICENSE
ddg2rss-1.0.1.dist-info/METADATA
ddg2rss-1.0.1.dist-info/WHEEL
ddg2rss-1.0.1.dist-info/top_level.txt
ddg2rss-1.0.1.dist-info/RECORD
