Metadata-Version: 2.2
Name: ddg2rss
Version: 1.0.1
Summary: Convert DuckduckGo News to RSS feed
Author-email: Thibaut_S <py@spriet.online>
License: MIT-License
Project-URL: Homepage, https://gitlab.com/Thibaut_S/ddg2rss
Project-URL: Bug Tracker, https://gitlab.com/Thibaut_S/ddg2rss/-/issues
Keywords: rss,feed,ddg
Classifier: Programming Language :: Python :: 3
Requires-Python: >=3.11
License-File: LICENSE
Requires-Dist: duckduckgo-search
Requires-Dist: feedgen
Requires-Dist: python-slugify
Provides-Extra: dev
Requires-Dist: wheel; extra == "dev"
Requires-Dist: pytest; extra == "dev"
Requires-Dist: ruff; extra == "dev"
Requires-Dist: black; extra == "dev"
Requires-Dist: pip-tools; extra == "dev"
Requires-Dist: twine; extra == "dev"
